<?xml version="1.0" encoding="UTF-8" standalone="yes"?>
<Properties xmlns="http://schemas.openxmlformats.org/officeDocument/2006/extended-properties" xmlns:vt="http://schemas.openxmlformats.org/officeDocument/2006/docPropsVTypes"><Template>Office Theme</Template><TotalTime>367</TotalTime><Words>9</Words><Application>Microsoft Office PowerPoint</Application><PresentationFormat>Personalizar</PresentationFormat><Paragraphs>5</Paragraphs><Slides>1</Slides><Notes>0</Notes><HiddenSlides>0</HiddenSlides><MMClips>0</MMClips><ScaleCrop>false</ScaleCrop><HeadingPairs><vt:vector size="6" baseType="variant"><vt:variant><vt:lpstr>Fontes usadas</vt:lpstr></vt:variant><vt:variant><vt:i4>3</vt:i4></vt:variant><vt:variant><vt:lpstr>Tema</vt:lpstr></vt:variant><vt:variant><vt:i4>1</vt:i4></vt:variant><vt:variant><vt:lpstr>Títulos de slides</vt:lpstr></vt:variant><vt:variant><vt:i4>1</vt:i4></vt:variant></vt:vector></HeadingPairs><TitlesOfParts><vt:vector size="5" baseType="lpstr"><vt:lpstr>Arial</vt:lpstr><vt:lpstr>Calibri</vt:lpstr><vt:lpstr>Calibri Light</vt:lpstr><vt:lpstr>Tema do Office</vt:lpstr><vt:lpstr>Apresentação do PowerPoint</vt:lpstr></vt:vector></TitlesOfParts><Company></Company><LinksUpToDate>false</LinksUpToDate><SharedDoc>false</SharedDoc><HyperlinksChanged>false</HyperlinksChanged><AppVersion>15.0000</AppVersion></Properties>